servicehandler/__init__.py
servicehandler/servicehandler.py
servicehandler/servicestate.py
servicehandler/utils.py
servicehandler-0.9.dist-info/LICENSE
servicehandler-0.9.dist-info/METADATA
servicehandler-0.9.dist-info/WHEEL
servicehandler-0.9.dist-info/top_level.txt
servicehandler-0.9.dist-info/RECORD
