Metadata-Version: 2.1
Name: servicehandler
Version: 0.9
Summary: Systemd service handler
Home-page: https://github.com/albertosantagostino/systemd-servicehandler
Author: Alberto Santagostino
License: MIT
Keywords: Systemd Service Daemon Handler Linux Unix
Platform: UNKNOWN
Classifier: Programming Language :: Python :: 3
Classifier: License :: OSI Approved :: MIT License
Requires-Python: >=3.6
